secp256k1prp/__init__.py
secp256k1prp/__main__.py
secp256k1prp/_libsecp256k1.cpython-35m-darwin.so
secp256k1prp-0.13.3.dist-info/METADATA
secp256k1prp-0.13.3.dist-info/RECORD
secp256k1prp-0.13.3.dist-info/WHEEL
secp256k1prp-0.13.3.dist-info/top_level.txt
